template_data/__init__.py
template_data/admin.py
template_data/apps.py
template_data/models.py
template_data/processors.py
template_data/management/__init__.py
template_data/management/commands/__init__.py
template_data/management/commands/add_data.py
template_data/management/commands/restore_data.py
template_data/management/commands/rewrite_template.py
template_data/management/commands/save_data.py
template_data/migrations/0001_initial.py
template_data/migrations/0002_templatedata_lang_alter_templatedata_id.py
template_data/migrations/__init__.py
django_template_data-0.1.1.dist-info/LICENSE
django_template_data-0.1.1.dist-info/METADATA
django_template_data-0.1.1.dist-info/WHEEL
django_template_data-0.1.1.dist-info/top_level.txt
django_template_data-0.1.1.dist-info/RECORD
