Metadata-Version: 2.1
Name: django-template-data
Version: 0.1.1
Summary: A library to load data from database to template
Home-page: https://github.com/jefcolbi/django-template-data
Author: jefcolbi
Author-email: jefcolbi@gmail.com
License: MIT
Platform: UNKNOWN
Classifier: Natural Language :: English
Classifier: Natural Language :: French
Classifier: Development Status :: 3 - Alpha
Classifier: Programming Language :: Python
Classifier: Programming Language :: Python :: 3.5
Classifier: Programming Language :: Python :: 3.6
Classifier: Programming Language :: Python :: 3.7
Classifier: License :: OSI Approved :: GNU General Public License v3 or later (GPLv3+)
Requires-Python: >=3.5
Requires-Dist: django >=3.0
Requires-Dist: html5-parser
Requires-Dist: lxml
Provides-Extra: meta
Requires-Dist: django-meta ; extra == 'meta'
